sowing/__init__.py
sowing/indexed.py
sowing/node.py
sowing/traversal.py
sowing/zipper.py
sowing/cli/__main__.py
sowing/comb/binary.py
sowing/comb/supertree.py
sowing/repr/json.py
sowing/repr/newick/__init__.py
sowing/repr/newick/parse.py
sowing/repr/newick/write.py
sowing/util/dataclasses.py
sowing/util/partition.py
sowing/util/rangequery.py
sowing-0.1.0.dist-info/METADATA
sowing-0.1.0.dist-info/WHEEL
sowing-0.1.0.dist-info/entry_points.txt
sowing-0.1.0.dist-info/licenses/LICENSE
sowing-0.1.0.dist-info/RECORD
