Metadata-Version: 2.4
Name: sowing
Version: 0.1.0
Summary: sowing
Project-URL: Homepage, https://github.com/UdeM-LBIT/sowing
Project-URL: Bug Tracker, https://github.com/UdeM-LBIT/sowing/issues
Author-email: Mattéo Delabre <git.matteo@delab.re>
License-File: LICENSE
Classifier: License :: OSI Approved :: GNU General Public License v3 or later (GPLv3+)
Classifier: Operating System :: OS Independent
Classifier: Programming Language :: Python :: 3
Requires-Python: >=3.11
Requires-Dist: immutables
